funAmpliacion/__init__.py
funAmpliacion/funciones.py
funampliacion_ngp-0.1.2.dist-info/licenses/LICENSE
funampliacion_ngp-0.1.2.dist-info/METADATA
funampliacion_ngp-0.1.2.dist-info/WHEEL
funampliacion_ngp-0.1.2.dist-info/top_level.txt
funampliacion_ngp-0.1.2.dist-info/RECORD
