Metadata-Version: 2.4
Name: funAmpliacion_ngp
Version: 0.1.2
Summary: Libreria
Author: Nicolás Guañuna
Requires-Python: >=3.8
License-File: LICENSE
Dynamic: license-file
